exbook/__init__.py
exbook/exbook.py
exbook/setup.py
exbook-0.0.5.dist-info/METADATA
exbook-0.0.5.dist-info/WHEEL
exbook-0.0.5.dist-info/top_level.txt
exbook-0.0.5.dist-info/RECORD
