Metadata-Version: 2.1
Name: exbook
Version: 0.0.5
Summary: Exercises for Python coding
Home-page: https://github.com/XiongPengNUS/exbook
Author: Peng Xiong
Author-email: xiongpengnus@gmail.com
License: UNKNOWN
Platform: UNKNOWN
Classifier: Programming Language :: Python :: 3
Classifier: Operating System :: OS Independent
